w4/lab08/fibonacci_generator.v
module fibonacci_generator (
    input clk,        // Clock signal
    input rst,        // Synchronous reset
    input enable,     // Enable signal for calculating next Fibonacci number
    output reg [31:0] fib_out  // Output for the current Fibonacci number
);

reg [31:0] fib_prev1;  // F(n-1)
reg [31:0] fib_prev2;  // F(n-2)
reg [31:0] fib_out1;

assign fib_out = fib_out1;

always @(posedge clk) begin
    if (rst) begin
        // Initialize Fibonacci numbers
        fib_prev1 = 32'd1;  // F(1) = 1
        fib_prev2 = 32'd0;  // F(0) = 0
        fib_out1 = 32'd0;    // Current Fibonacci number = F(0)
    end else if (enable) begin
        // Compute next Fibonacci number
        fib_out1 = fib_prev1 + fib_prev2;

        // Update previous Fibonacci numbers
        fib_prev2 = fib_prev1;
        fib_prev1 = fib_out1;
    end
end

endmodule

w4/lab08/correct_fib_gen.vcd
$version Generated by VerilatedVcd $end
$timescale 1ps $end
 $scope module TOP $end
  $var wire 1 & clk $end
  $var wire 1 ' rst $end
  $var wire 1 ( enable $end
  $var wire 32 ) fib_out [31:0] $end
  $scope module fibonacci_generator $end
   $var wire 1 & clk $end
   $var wire 1 ' rst $end
   $var wire 1 ( enable $end
   $var wire 32 ) fib_out [31:0] $end
   $var wire 32 # fib_prev1 [31:0] $end
   $var wire 32 $ fib_prev2 [31:0] $end
   $var wire 32 % fib_out1 [31:0] $end
  $upscope $end
 $upscope $end
$enddefinitions $end


#0
b00000000000000000000000000000000 #
b00000000000000000000000000000000 $
b00000000000000000000000000000000 %
1&
1'
1(
b00000000000000000000000000000000 )
#1
0&
#2
b00000000000000000000000000000001 #
1&
#3
0&
#4
1&
#5
0&
#6
1&
#7
0&
#8
1&
#9
0&
#10
b00000000000000000000000000000001 $
b00000000000000000000000000000001 %
1&
0'
b00000000000000000000000000000001 )
#11
0&
#12
b00000000000000000000000000000010 #
b00000000000000000000000000000010 %
1&
b00000000000000000000000000000010 )
#13
0&
#14
b00000000000000000000000000000011 #
b00000000000000000000000000000010 $
b00000000000000000000000000000011 %
1&
b00000000000000000000000000000011 )
#15
0&
#16
b00000000000000000000000000000101 #
b00000000000000000000000000000011 $
b00000000000000000000000000000101 %
1&
b00000000000000000000000000000101 )
#17
0&
#18
b00000000000000000000000000001000 #
b00000000000000000000000000000101 $
b00000000000000000000000000001000 %
1&
b00000000000000000000000000001000 )
#19
0&
#20
b00000000000000000000000000001101 #
b00000000000000000000000000001000 $
b00000000000000000000000000001101 %
1&
b00000000000000000000000000001101 )
#21
0&
#22
b00000000000000000000000000010101 #
b00000000000000000000000000001101 $
b00000000000000000000000000010101 %
1&
b00000000000000000000000000010101 )
#23
0&
#24
b00000000000000000000000000100010 #
b00000000000000000000000000010101 $
b00000000000000000000000000100010 %
1&
b00000000000000000000000000100010 )
#25
0&
#26
b00000000000000000000000000110111 #
b00000000000000000000000000100010 $
b00000000000000000000000000110111 %
1&
b00000000000000000000000000110111 )
#27
0&
#28
b00000000000000000000000001011001 #
b00000000000000000000000000110111 $
b00000000000000000000000001011001 %
1&
b00000000000000000000000001011001 )
#29
0&
#30
b00000000000000000000000010010000 #
b00000000000000000000000001011001 $
b00000000000000000000000010010000 %
1&
b00000000000000000000000010010000 )
#31
0&
#32
b00000000000000000000000011101001 #
b00000000000000000000000010010000 $
b00000000000000000000000011101001 %
1&
b00000000000000000000000011101001 )
#33
0&
#34
b00000000000000000000000101111001 #
b00000000000000000000000011101001 $
b00000000000000000000000101111001 %
1&
b00000000000000000000000101111001 )
#35
0&
#36
b00000000000000000000001001100010 #
b00000000000000000000000101111001 $
b00000000000000000000001001100010 %
1&
b00000000000000000000001001100010 )
#37
0&
#38
b00000000000000000000001111011011 #
b00000000000000000000001001100010 $
b00000000000000000000001111011011 %
1&
b00000000000000000000001111011011 )
#39
0&
#40
b00000000000000000000011000111101 #
b00000000000000000000001111011011 $
b00000000000000000000011000111101 %
1&
b00000000000000000000011000111101 )
#41
0&
#42
b00000000000000000000101000011000 #
b00000000000000000000011000111101 $
b00000000000000000000101000011000 %
1&
b00000000000000000000101000011000 )
#43
0&
#44
b00000000000000000001000001010101 #
b00000000000000000000101000011000 $
b00000000000000000001000001010101 %
1&
b00000000000000000001000001010101 )
#45
0&
#46
b00000000000000000001101001101101 #
b00000000000000000001000001010101 $
b00000000000000000001101001101101 %
1&
b00000000000000000001101001101101 )
#47
0&
#48
b00000000000000000010101011000010 #
b00000000000000000001101001101101 $
b00000000000000000010101011000010 %
1&
b00000000000000000010101011000010 )
#49
0&
#50
b00000000000000000100010100101111 #
b00000000000000000010101011000010 $
b00000000000000000100010100101111 %
1&
b00000000000000000100010100101111 )
#51
0&
#52
b00000000000000000110111111110001 #
b00000000000000000100010100101111 $
b00000000000000000110111111110001 %
1&
b00000000000000000110111111110001 )
#53
0&
#54
b00000000000000001011010100100000 #
b00000000000000000110111111110001 $
b00000000000000001011010100100000 %
1&
b00000000000000001011010100100000 )
#55
0&
#56
b00000000000000010010010100010001 #
b00000000000000001011010100100000 $
b00000000000000010010010100010001 %
1&
b00000000000000010010010100010001 )
#57
0&
#58
b00000000000000011101101000110001 #
b00000000000000010010010100010001 $
b00000000000000011101101000110001 %
1&
b00000000000000011101101000110001 )
#59
0&
#60
b00000000000000101111111101000010 #
b00000000000000011101101000110001 $
b00000000000000101111111101000010 %
1&
b00000000000000101111111101000010 )
#61
0&
#62
b00000000000001001101100101110011 #
b00000000000000101111111101000010 $
b00000000000001001101100101110011 %
1&
b00000000000001001101100101110011 )
#63
0&
#64
b00000000000001111101100010110101 #
b00000000000001001101100101110011 $
b00000000000001111101100010110101 %
1&
b00000000000001111101100010110101 )
#65
0&
#66
b00000000000011001011001000101000 #
b00000000000001111101100010110101 $
b00000000000011001011001000101000 %
1&
b00000000000011001011001000101000 )
#67
0&
#68
b00000000000101001000101011011101 #
b00000000000011001011001000101000 $
b00000000000101001000101011011101 %
1&
b00000000000101001000101011011101 )
#69
0&
#70
b00000000001000010011110100000101 #
b00000000000101001000101011011101 $
b00000000001000010011110100000101 %
1&
b00000000001000010011110100000101 )
#71
0&
#72
b00000000001101011100011111100010 #
b00000000001000010011110100000101 $
b00000000001101011100011111100010 %
1&
b00000000001101011100011111100010 )
#73
0&
#74
b00000000010101110000010011100111 #
b00000000001101011100011111100010 $
b00000000010101110000010011100111 %
1&
b00000000010101110000010011100111 )
#75
0&
#76
b00000000100011001100110011001001 #
b00000000010101110000010011100111 $
b00000000100011001100110011001001 %
1&
b00000000100011001100110011001001 )
#77
0&
#78
b00000000111000111101000110110000 #
b00000000100011001100110011001001 $
b00000000111000111101000110110000 %
1&
b00000000111000111101000110110000 )
#79
0&
#80
b00000001011100001001111001111001 #
b00000000111000111101000110110000 $
b00000001011100001001111001111001 %
1&
b00000001011100001001111001111001 )
#81
0&
#82
b00000010010101000111000000101001 #
b00000001011100001001111001111001 $
b00000010010101000111000000101001 %
1&
b00000010010101000111000000101001 )
#83
0&
#84
b00000011110001010000111010100010 #
b00000010010101000111000000101001 $
b00000011110001010000111010100010 %
1&
b00000011110001010000111010100010 )
#85
0&
#86
b00000110000110010111111011001011 #
b00000011110001010000111010100010 $
b00000110000110010111111011001011 %
1&
b00000110000110010111111011001011 )
#87
0&
#88
b00001001110111101000110101101101 #
b00000110000110010111111011001011 $
b00001001110111101000110101101101 %
1&
b00001001110111101000110101101101 )
#89
0&
#90
b00001111111110000000110000111000 #
b00001001110111101000110101101101 $
b00001111111110000000110000111000 %
1&
b00001111111110000000110000111000 )
#91
0&
#92
b00011001110101101001100110100101 #
b00001111111110000000110000111000 $
b00011001110101101001100110100101 %
1&
b00011001110101101001100110100101 )
#93
0&
#94
b00101001110011101010010111011101 #
b00011001110101101001100110100101 $
b00101001110011101010010111011101 %
1&
b00101001110011101010010111011101 )
#95
0&
#96
b01000011101001010011111110000010 #
b00101001110011101010010111011101 $
b01000011101001010011111110000010 %
1&
b01000011101001010011111110000010 )
#97
0&
#98
b01101101011100111110010101011111 #
b01000011101001010011111110000010 $
b01101101011100111110010101011111 %
1&
b01101101011100111110010101011111 )
#99
0&
#100
b10110001000110010010010011100001 #
b01101101011100111110010101011111 $
b10110001000110010010010011100001 %
1&
b10110001000110010010010011100001 )
#101
0&
#102
b00011110100011010000101001000000 #
b10110001000110010010010011100001 $
b00011110100011010000101001000000 %
1&
b00011110100011010000101001000000 )
#103
0&
#104
b11001111101001100010111100100001 #
b00011110100011010000101001000000 $
b11001111101001100010111100100001 %
1&
b11001111101001100010111100100001 )
#105
0&
#106
b11101110001100110011100101100001 #
b11001111101001100010111100100001 $
b11101110001100110011100101100001 %
1&
b11101110001100110011100101100001 )
#107
0&
#108
b10111101110110010110100010000010 #
b11101110001100110011100101100001 $
b10111101110110010110100010000010 %
1&
b10111101110110010110100010000010 )
#109
0&
#110
b10101100000011001010000111100011 #
b10111101110110010110100010000010 $
b10101100000011001010000111100011 %
1&
b10101100000011001010000111100011 )
#111
0&
#112
b01101001111001100000101001100101 #
b10101100000011001010000111100011 $
b01101001111001100000101001100101 %
1&
b01101001111001100000101001100101 )
#113
0&
#114
b00010101111100101010110001001000 #
b01101001111001100000101001100101 $
b00010101111100101010110001001000 %
1&
b00010101111100101010110001001000 )
#115
0&
#116
b01111111110110001011011010101101 #
b00010101111100101010110001001000 $
b01111111110110001011011010101101 %
1&
b01111111110110001011011010101101 )
#117
0&
#118
b10010101110010110110001011110101 #
b01111111110110001011011010101101 $
b10010101110010110110001011110101 %
1&
b10010101110010110110001011110101 )
#119
0&
#120
b00010101101001000001100110100010 #
b10010101110010110110001011110101 $
b00010101101001000001100110100010 %
1&
b00010101101001000001100110100010 )
#121
0&
#122
b10101011011011110111110010010111 #
b00010101101001000001100110100010 $
b10101011011011110111110010010111 %
1&
b10101011011011110111110010010111 )
#123
0&
#124
b11000001000100111001011000111001 #
b10101011011011110111110010010111 $
b11000001000100111001011000111001 %
1&
b11000001000100111001011000111001 )
#125
0&
#126
b01101100100000110001001011010000 #
b11000001000100111001011000111001 $
b01101100100000110001001011010000 %
1&
b01101100100000110001001011010000 )
#127
0&
#128
b00101101100101101010100100001001 #
b01101100100000110001001011010000 $
b00101101100101101010100100001001 %
1&
b00101101100101101010100100001001 )
#129
0&
#130
b10011010000110011011101111011001 #
b00101101100101101010100100001001 $
b10011010000110011011101111011001 %
1&
b10011010000110011011101111011001 )
#131
0&
#132
b11000111101100000110010011100010 #
b10011010000110011011101111011001 $
b11000111101100000110010011100010 %
1&
b11000111101100000110010011100010 )
#133
0&
#134
b01100001110010100010000010111011 #
b11000111101100000110010011100010 $
b01100001110010100010000010111011 %
1&
b01100001110010100010000010111011 )
#135
0&
#136
b00101001011110101000010110011101 #
b01100001110010100010000010111011 $
b00101001011110101000010110011101 %
1&
b00101001011110101000010110011101 )
#137
0&
#138
b10001011010001001010011001011000 #
b00101001011110101000010110011101 $
b10001011010001001010011001011000 %
1&
b10001011010001001010011001011000 )
#139
0&
#140
b10110100101111110010101111110101 #
b10001011010001001010011001011000 $
b10110100101111110010101111110101 %
1&
b10110100101111110010101111110101 )
#141
0&
#142
b01000000000000111101001001001101 #
b10110100101111110010101111110101 $
b01000000000000111101001001001101 %
1&
b01000000000000111101001001001101 )
#143
0&
#144
b11110100110000101111111001000010 #
b01000000000000111101001001001101 $
b11110100110000101111111001000010 %
1&
b11110100110000101111111001000010 )
#145
0&
#146
b00110100110001101101000010001111 #
b11110100110000101111111001000010 $
b00110100110001101101000010001111 %
1&
b00110100110001101101000010001111 )
#147
0&
#148
b00101001100010011100111011010001 #
b00110100110001101101000010001111 $
b00101001100010011100111011010001 %
1&
b00101001100010011100111011010001 )
#149
0&
#150
b01011110010100001001111101100000 #
b00101001100010011100111011010001 $
b01011110010100001001111101100000 %
1&
b01011110010100001001111101100000 )
#151
0&
#152
b10000111110110100110111000110001 #
b01011110010100001001111101100000 $
b10000111110110100110111000110001 %
1&
b10000111110110100110111000110001 )
#153
0&
#154
b11100110001010110000110110010001 #
b10000111110110100110111000110001 $
b11100110001010110000110110010001 %
1&
b11100110001010110000110110010001 )
#155
0&
#156
b01101110000001010111101111000010 #
b11100110001010110000110110010001 $
b01101110000001010111101111000010 %
1&
b01101110000001010111101111000010 )
#157
0&
#158
b01010100001100001000100101010011 #
b01101110000001010111101111000010 $
b01010100001100001000100101010011 %
1&
b01010100001100001000100101010011 )
#159
0&
#160
b11000010001101100000010100010101 #
b01010100001100001000100101010011 $
b11000010001101100000010100010101 %
1&
b11000010001101100000010100010101 )
#161
0&
#162
b00010110011001101000111001101000 #
b11000010001101100000010100010101 $
b00010110011001101000111001101000 %
1&
b00010110011001101000111001101000 )
#163
0&
#164
b11011000100111001001001101111101 #
b00010110011001101000111001101000 $
b11011000100111001001001101111101 %
1&
b11011000100111001001001101111101 )
#165
0&
#166
b11101111000000110010000111100101 #
b11011000100111001001001101111101 $
b11101111000000110010000111100101 %
1&
b11101111000000110010000111100101 )
#167
0&
#168
b11000111100111111011010101100010 #
b11101111000000110010000111100101 $
b11000111100111111011010101100010 %
1&
b11000111100111111011010101100010 )
#169
0&
#170
b10110110101000101101011101000111 #
b11000111100111111011010101100010 $
b10110110101000101101011101000111 %
1&
b10110110101000101101011101000111 )
#171
0&
#172
b01111110010000101000110010101001 #
b10110110101000101101011101000111 $
b01111110010000101000110010101001 %
1&
b01111110010000101000110010101001 )
#173
0&
#174
b00110100111001010110001111110000 #
b01111110010000101000110010101001 $
b00110100111001010110001111110000 %
1&
b00110100111001010110001111110000 )
#175
0&
#176
b10110011001001111111000010011001 #
b00110100111001010110001111110000 $
b10110011001001111111000010011001 %
1&
b10110011001001111111000010011001 )
#177
0&
#178
b11101000000011010101010010001001 #
b10110011001001111111000010011001 $
b11101000000011010101010010001001 %
1&
b11101000000011010101010010001001 )
#179
0&
#180
b10011011001101010100010100100010 #
b11101000000011010101010010001001 $
b10011011001101010100010100100010 %
1&
b10011011001101010100010100100010 )
#181
0&
#182
b10000011010000101001100110101011 #
b10011011001101010100010100100010 $
b10000011010000101001100110101011 %
1&
b10000011010000101001100110101011 )
#183
0&
#184
b00011110011101111101111011001101 #
b10000011010000101001100110101011 $
b00011110011101111101111011001101 %
1&
b00011110011101111101111011001101 )
#185
0&
#186
b10100001101110100111100001111000 #
b00011110011101111101111011001101 $
b10100001101110100111100001111000 %
1&
b10100001101110100111100001111000 )
#187
0&
#188
b11000000001100100101011101000101 #
b10100001101110100111100001111000 $
b11000000001100100101011101000101 %
1&
b11000000001100100101011101000101 )
#189
0&
#190
b01100001111011001100111110111101 #
b11000000001100100101011101000101 $
b01100001111011001100111110111101 %
1&
b01100001111011001100111110111101 )
#191
0&
#192
b00100010000111110010011100000010 #
b01100001111011001100111110111101 $
b00100010000111110010011100000010 %
1&
b00100010000111110010011100000010 )
#193
0&
#194
b10000100000010111111011010111111 #
b00100010000111110010011100000010 $
b10000100000010111111011010111111 %
1&
b10000100000010111111011010111111 )
#195
0&
#196
b10100110001010110001110111000001 #
b10000100000010111111011010111111 $
b10100110001010110001110111000001 %
1&
b10100110001010110001110111000001 )
#197
0&
#198
b00101010001101110001010010000000 #
b10100110001010110001110111000001 $
b00101010001101110001010010000000 %
1&
b00101010001101110001010010000000 )
#199
0&
#200
b11010000011000100011001001000001 #
b00101010001101110001010010000000 $
b11010000011000100011001001000001 %
1&
b11010000011000100011001001000001 )
#201
0&
#202
b11111010100110010100011011000001 #
b11010000011000100011001001000001 $
b11111010100110010100011011000001 %
1&
b11111010100110010100011011000001 )
#203
0&
#204
b11001010111110110111100100000010 #
b11111010100110010100011011000001 $
b11001010111110110111100100000010 %
1&
b11001010111110110111100100000010 )
#205
0&
#206
b11000101100101001011111111000011 #
b11001010111110110111100100000010 $
b11000101100101001011111111000011 %
1&
b11000101100101001011111111000011 )
#207
0&
#208
b10010000100100000011100011000101 #
b11000101100101001011111111000011 $
b10010000100100000011100011000101 %
1&
b10010000100100000011100011000101 )
#209
0&
#210
b01010110001001001111100010001000 #
b10010000100100000011100011000101 $
b01010110001001001111100010001000 %
1&
b01010110001001001111100010001000 )
#211
0&
#212
b11100110101101010011000101001101 #
b01010110001001001111100010001000 $
b11100110101101010011000101001101 %
1&
b11100110101101010011000101001101 )
#213
0&
#214
b00111100110110100010100111010101 #
b11100110101101010011000101001101 $
b00111100110110100010100111010101 %
1&
b00111100110110100010100111010101 )
#215
0&
#216
b00100011100011110101101100100010 #
b00111100110110100010100111010101 $
b00100011100011110101101100100010 %
1&
b00100011100011110101101100100010 )
#217
0&
#218
b01100000011010011000010011110111 #
b00100011100011110101101100100010 $
b01100000011010011000010011110111 %
1&
b01100000011010011000010011110111 )
#219
0&
#220
b10000011111110001110000000011001 #
b01100000011010011000010011110111 $
b10000011111110001110000000011001 %
1&
b10000011111110001110000000011001 )
#221
0&
#222
b11100100011000100110010100010000 #
b10000011111110001110000000011001 $
b11100100011000100110010100010000 %
1&
b11100100011000100110010100010000 )
#223
0&
#224
b01101000010110110100010100101001 #
b11100100011000100110010100010000 $
b01101000010110110100010100101001 %
1&
b01101000010110110100010100101001 )
#225
0&
#226
b01001100101111011010101000111001 #
b01101000010110110100010100101001 $
b01001100101111011010101000111001 %
1&
b01001100101111011010101000111001 )
#227
0&
#228
b10110101000110001110111101100010 #
b01001100101111011010101000111001 $
b10110101000110001110111101100010 %
1&
b10110101000110001110111101100010 )
#229
0&
#230
b00000001110101101001100110011011 #
b10110101000110001110111101100010 $
b00000001110101101001100110011011 %
1&
b00000001110101101001100110011011 )
#231
0&
#232
b10110110111011111000100011111101 #
b00000001110101101001100110011011 $
b10110110111011111000100011111101 %
1&
b10110110111011111000100011111101 )
#233
0&
#234
b10111000110001100010001010011000 #
b10110110111011111000100011111101 $
b10111000110001100010001010011000 %
1&
b10111000110001100010001010011000 )
#235
0&
#236
b01101111101101011010101110010101 #
b10111000110001100010001010011000 $
b01101111101101011010101110010101 %
1&
b01101111101101011010101110010101 )
#237
0&
#238
b00101000011110111100111000101101 #
b01101111101101011010101110010101 $
b00101000011110111100111000101101 %
1&
b00101000011110111100111000101101 )
#239
0&
#240
b10011000001100010111100111000010 #
b00101000011110111100111000101101 $
b10011000001100010111100111000010 %
1&
b10011000001100010111100111000010 )
#241
0&
#242
b11000000101011010100011111101111 #
b10011000001100010111100111000010 $
b11000000101011010100011111101111 %
1&
b11000000101011010100011111101111 )
#243
0&
#244
b01011000110111101100000110110001 #
b11000000101011010100011111101111 $
b01011000110111101100000110110001 %
1&
b01011000110111101100000110110001 )
#245
0&
#246
b00011001100011000000100110100000 #
b01011000110111101100000110110001 $
b00011001100011000000100110100000 %
1&
b00011001100011000000100110100000 )
#247
0&
#248
b01110010011010101100101101010001 #
b00011001100011000000100110100000 $
b01110010011010101100101101010001 %
1&
b01110010011010101100101101010001 )
#249
0&
#250
b10001011111101101101010011110001 #
b01110010011010101100101101010001 $
b10001011111101101101010011110001 %
1&
b10001011111101101101010011110001 )
#251
0&
#252
b11111110011000011010000001000010 #
b10001011111101101101010011110001 $
b11111110011000011010000001000010 %
1&
b11111110011000011010000001000010 )
#253
0&
#254
b10001010010110000111010100110011 #
b11111110011000011010000001000010 $
b10001010010110000111010100110011 %
1&
b10001010010110000111010100110011 )
#255
0&
#256
b10001000101110100001010101110101 #
b10001010010110000111010100110011 $
b10001000101110100001010101110101 %
1&
b10001000101110100001010101110101 )
#257
0&
#258
b00010011000100101000101010101000 #
b10001000101110100001010101110101 $
b00010011000100101000101010101000 %
1&
b00010011000100101000101010101000 )
#259
0&
#260
b10011011110011001010000000011101 #
b00010011000100101000101010101000 $
b10011011110011001010000000011101 %
1&
b10011011110011001010000000011101 )
#261
0&
#262
b10101110110111110010101011000101 #
b10011011110011001010000000011101 $
b10101110110111110010101011000101 %
1&
b10101110110111110010101011000101 )
#263
0&
#264
b01001010101010111100101011100010 #
b10101110110111110010101011000101 $
b01001010101010111100101011100010 %
1&
b01001010101010111100101011100010 )
#265
0&
#266
b11111001100010101111010110100111 #
b01001010101010111100101011100010 $
b11111001100010101111010110100111 %
1&
b11111001100010101111010110100111 )
#267
0&
#268
b01000100001101101100000010001001 #
b11111001100010101111010110100111 $
b01000100001101101100000010001001 %
1&
b01000100001101101100000010001001 )
#269
0&
#270
b00111101110000011011011000110000 #
b01000100001101101100000010001001 $
b00111101110000011011011000110000 %
1&
b00111101110000011011011000110000 )
#271
0&
#272
b10000001111110000111011010111001 #
b00111101110000011011011000110000 $
b10000001111110000111011010111001 %
1&
b10000001111110000111011010111001 )
#273
0&
#274
b10111111101110100010110011101001 #
b10000001111110000111011010111001 $
b10111111101110100010110011101001 %
1&
b10111111101110100010110011101001 )
#275
0&
#276
b01000001101100101010001110100010 #
b10111111101110100010110011101001 $
b01000001101100101010001110100010 %
1&
b01000001101100101010001110100010 )
#277
0&
#278
b00000001011011001101000010001011 #
b01000001101100101010001110100010 $
b00000001011011001101000010001011 %
1&
b00000001011011001101000010001011 )
#279
0&
#280
b01000011000111110111010000101101 #
b00000001011011001101000010001011 $
b01000011000111110111010000101101 %
1&
b01000011000111110111010000101101 )
#281
0&
#282
b01000100100011000100010010111000 #
b01000011000111110111010000101101 $
b01000100100011000100010010111000 %
1&
b01000100100011000100010010111000 )
#283
0&
#284
b10000111101010111011100011100101 #
b01000100100011000100010010111000 $
b10000111101010111011100011100101 %
1&
b10000111101010111011100011100101 )
#285
0&
#286
b11001100001101111111110110011101 #
b10000111101010111011100011100101 $
b11001100001101111111110110011101 %
1&
b11001100001101111111110110011101 )
#287
0&
#288
b01010011111000111011011010000010 #
b11001100001101111111110110011101 $
b01010011111000111011011010000010 %
1&
b01010011111000111011011010000010 )
#289
0&
#290
b00100000000110111011010000011111 #
b01010011111000111011011010000010 $
b00100000000110111011010000011111 %
1&
b00100000000110111011010000011111 )
#291
0&
#292
b01110011111111110110101010100001 #
b00100000000110111011010000011111 $
b01110011111111110110101010100001 %
1&
b01110011111111110110101010100001 )
#293
0&
#294
b10010100000110110001111011000000 #
b01110011111111110110101010100001 $
b10010100000110110001111011000000 %
1&
b10010100000110110001111011000000 )
#295
0&
#296
b00001000000110101000100101100001 #
b10010100000110110001111011000000 $
b00001000000110101000100101100001 %
1&
b00001000000110101000100101100001 )
#297
0&
#298
b10011100001101011010100000100001 #
b00001000000110101000100101100001 $
b10011100001101011010100000100001 %
1&
b10011100001101011010100000100001 )
#299
0&
#300
b10100100010100000011000110000010 #
b10011100001101011010100000100001 $
b10100100010100000011000110000010 %
1&
b10100100010100000011000110000010 )
#301
0&
#302
b01000000100001011101100110100011 #
b10100100010100000011000110000010 $
b01000000100001011101100110100011 %
1&
b01000000100001011101100110100011 )
#303
0&
#304
b11100100110101100000101100100101 #
b01000000100001011101100110100011 $
b11100100110101100000101100100101 %
1&
b11100100110101100000101100100101 )
#305
0&
#306
b00100101010110111110010011001000 #
b11100100110101100000101100100101 $
b00100101010110111110010011001000 %
1&
b00100101010110111110010011001000 )
#307
0&
#308
b00001010001100011110111111101101 #
b00100101010110111110010011001000 $
b00001010001100011110111111101101 %
1&
b00001010001100011110111111101101 )
#309
0&
#310
b00101111100011011101010010110101 #
b00001010001100011110111111101101 $
b00101111100011011101010010110101 %
1&
b00101111100011011101010010110101 )
#311
0&
#312
b00111001101111111100010010100010 #
b00101111100011011101010010110101 $
b00111001101111111100010010100010 %
1&
b00111001101111111100010010100010 )
#313
0&
#314
b01101001010011011001100101010111 #
b00111001101111111100010010100010 $
b01101001010011011001100101010111 %
1&
b01101001010011011001100101010111 )
#315
0&
#316
b10100011000011010101110111111001 #
b01101001010011011001100101010111 $
b10100011000011010101110111111001 %
1&
b10100011000011010101110111111001 )
#317
0&
#318
b00001100010110101111011101010000 #
b10100011000011010101110111111001 $
b00001100010110101111011101010000 %
1&
b00001100010110101111011101010000 )
#319
0&
#320
b10101111011010000101010101001001 #
b00001100010110101111011101010000 $
b10101111011010000101010101001001 %
1&
b10101111011010000101010101001001 )
#321
0&
#322
b10111011110000110100110010011001 #
b10101111011010000101010101001001 $
b10111011110000110100110010011001 %
1&
b10111011110000110100110010011001 )
#323
0&
#324
b01101011001010111010000111100010 #
b10111011110000110100110010011001 $
b01101011001010111010000111100010 %
1&
b01101011001010111010000111100010 )
#325
0&
#326
b00100110111011101110111001111011 #
b01101011001010111010000111100010 $
b00100110111011101110111001111011 %
1&
b00100110111011101110111001111011 )
#327
0&
#328
b10010010000110101001000001011101 #
b00100110111011101110111001111011 $
b10010010000110101001000001011101 %
1&
b10010010000110101001000001011101 )
#329
0&
#330
b10111001000010010111111011011000 #
b10010010000110101001000001011101 $
b10111001000010010111111011011000 %
1&
b10111001000010010111111011011000 )
#331
0&
#332
b01001011001001000000111100110101 #
b10111001000010010111111011011000 $
b01001011001001000000111100110101 %
1&
b01001011001001000000111100110101 )
#333
0&
#334
b00000100001011011000111000001101 #
b01001011001001000000111100110101 $
b00000100001011011000111000001101 %
1&
b00000100001011011000111000001101 )
#335
0&
#336
b01001111010100011001110101000010 #
b00000100001011011000111000001101 $
b01001111010100011001110101000010 %
1&
b01001111010100011001110101000010 )
#337
0&
#338
b01010011011111110010101101001111 #
b01001111010100011001110101000010 $
b01010011011111110010101101001111 %
1&
b01010011011111110010101101001111 )
#339
0&
#340
b10100010110100001100100010010001 #
b01010011011111110010101101001111 $
b10100010110100001100100010010001 %
1&
b10100010110100001100100010010001 )
#341
0&
#342
b11110110010011111111001111100000 #
b10100010110100001100100010010001 $
b11110110010011111111001111100000 %
1&
b11110110010011111111001111100000 )
#343
0&
#344
b10011001001000001011110001110001 #
b11110110010011111111001111100000 $
b10011001001000001011110001110001 %
1&
b10011001001000001011110001110001 )
#345
0&
#346
b10001111011100001011000001010001 #
b10011001001000001011110001110001 $
b10001111011100001011000001010001 %
1&
b10001111011100001011000001010001 )
#347
0&
#348
b00101000100100010110110011000010 #
b10001111011100001011000001010001 $
b00101000100100010110110011000010 %
1&
b00101000100100010110110011000010 )
#349
0&
#350
b10111000000000100001110100010011 #
b00101000100100010110110011000010 $
b10111000000000100001110100010011 %
1&
b10111000000000100001110100010011 )
#351
0&
#352
b11100000100100111000100111010101 #
b10111000000000100001110100010011 $
b11100000100100111000100111010101 %
1&
b11100000100100111000100111010101 )
#353
0&
#354
b10011000100101011010011011101000 #
b11100000100100111000100111010101 $
b10011000100101011010011011101000 %
1&
b10011000100101011010011011101000 )
#355
0&
#356
b01111001001010010011000010111101 #
b10011000100101011010011011101000 $
b01111001001010010011000010111101 %
1&
b01111001001010010011000010111101 )
#357
0&
#358
b00010001101111101101011110100101 #
b01111001001010010011000010111101 $
b00010001101111101101011110100101 %
1&
b00010001101111101101011110100101 )
#359
0&
#360
b10001010111010000000100001100010 #
b00010001101111101101011110100101 $
b10001010111010000000100001100010 %
1&
b10001010111010000000100001100010 )
#361
0&
#362
b10011100101001101110000000000111 #
b10001010111010000000100001100010 $
b10011100101001101110000000000111 %
1&
b10011100101001101110000000000111 )
#363
0&
#364
b00100111100011101110100001101001 #
b10011100101001101110000000000111 $
b00100111100011101110100001101001 %
1&
b00100111100011101110100001101001 )
#365
0&
#366
b11000100001101011100100001110000 #
b00100111100011101110100001101001 $
b11000100001101011100100001110000 %
1&
b11000100001101011100100001110000 )
#367
0&
#368
b11101011110001001011000011011001 #
b11000100001101011100100001110000 $
b11101011110001001011000011011001 %
1&
b11101011110001001011000011011001 )
#369
0&
#370
b10101111111110100111100101001001 #
b11101011110001001011000011011001 $
b10101111111110100111100101001001 %
1&
b10101111111110100111100101001001 )
#371
0&
#372
b10011011101111110010101000100010 #
b10101111111110100111100101001001 $
b10011011101111110010101000100010 %
1&
b10011011101111110010101000100010 )
#373
0&
#374
b01001011101110011010001101101011 #
b10011011101111110010101000100010 $
b01001011101110011010001101101011 %
1&
b01001011101110011010001101101011 )
#375
0&
#376
b11100111011110001100110110001101 #
b01001011101110011010001101101011 $
b11100111011110001100110110001101 %
1&
b11100111011110001100110110001101 )
#377
0&
#378
b00110011001100100111000011111000 #
b11100111011110001100110110001101 $
b00110011001100100111000011111000 %
1&
b00110011001100100111000011111000 )
#379
0&
#380
b00011010101010110011111010000101 #
b00110011001100100111000011111000 $
b00011010101010110011111010000101 %
1&
b00011010101010110011111010000101 )
#381
0&
#382
b01001101110111011010111101111101 #
b00011010101010110011111010000101 $
b01001101110111011010111101111101 %
1&
b01001101110111011010111101111101 )
#383
0&
#384
b01101000100010001110111000000010 #
b01001101110111011010111101111101 $
b01101000100010001110111000000010 %
1&
b01101000100010001110111000000010 )
#385
0&
#386
b10110110011001101001110101111111 #
b01101000100010001110111000000010 $
b10110110011001101001110101111111 %
1&
b10110110011001101001110101111111 )
#387
0&
#388
b00011110111011111000101110000001 #
b10110110011001101001110101111111 $
b00011110111011111000101110000001 %
1&
b00011110111011111000101110000001 )
#389
0&
#390
b11010101010101100010100100000000 #
b00011110111011111000101110000001 $
b11010101010101100010100100000000 %
1&
b11010101010101100010100100000000 )
#391
0&
#392
b11110100010001011011010010000001 #
b11010101010101100010100100000000 $
b11110100010001011011010010000001 %
1&
b11110100010001011011010010000001 )
#393
0&
#394
b11001001100110111101110110000001 #
b11110100010001011011010010000001 $
b11001001100110111101110110000001 %
1&
b11001001100110111101110110000001 )
#395
0&
#396
b10111101111000011001001000000010 #
b11001001100110111101110110000001 $
b10111101111000011001001000000010 %
1&
b10111101111000011001001000000010 )
#397
0&
#398
b10000111011111010110111110000011 #
b10111101111000011001001000000010 $
b10000111011111010110111110000011 %
1&
b10000111011111010110111110000011 )
#399
0&
#400
b01000101010111110000000110000101 #
b10000111011111010110111110000011 $
b01000101010111110000000110000101 %
1&
b01000101010111110000000110000101 )
#401
0&
