w4/lab08/fibonacci_generator.v
module fibonacci_generator (
    input clk,        // Clock signal
    input rst,        // Synchronous reset
    input enable,     // Enable signal for calculating next Fibonacci number
    output reg [31:0] fib_out  // Output for the current Fibonacci number
);

reg [31:0] fib_prev1;  // F(n-1)
reg [31:0] fib_prev2;  // F(n-2)
reg [31:0] fib_out1;

assign fib_out = fib_out1;

always @(posedge clk) begin
    if (rst) begin
        // Initialize Fibonacci numbers
        fib_prev1 = 32'd1;  // F(1) = 1
        fib_prev2 = 32'd0;  // F(0) = 0
        fib_out1 = 32'd0;    // Current Fibonacci number = F(0)
    end else if (enable) begin
        // Compute next Fibonacci number
        fib_out1 = fib_prev1 + fib_prev2;

        // Update previous Fibonacci numbers
        fib_prev2 = fib_prev1;
        fib_prev1 = fib_out1;
    end
end

endmodule

w4/lab08/faulty_fib_gen.vcd
$version Generated by VerilatedVcd $end
$timescale 1ps $end
 $scope module TOP $end
  $var wire 1 & clk $end
  $var wire 1 ' rst $end
  $var wire 1 ( enable $end
  $var wire 32 ) fib_out [31:0] $end
  $scope module fibonacci_generator $end
   $var wire 1 & clk $end
   $var wire 1 ' rst $end
   $var wire 1 ( enable $end
   $var wire 32 ) fib_out [31:0] $end
   $var wire 32 # fib_prev1 [31:0] $end
   $var wire 32 $ fib_prev2 [31:0] $end
   $var wire 32 % fib_out1 [31:0] $end
  $upscope $end
 $upscope $end
$enddefinitions $end


#0
b00000000000000000000000000000000 #
b00000000000000000000000000000000 $
b00000000000000000000000000000000 %
1&
1'
1(
b00000000000000000000000000000000 )
#1
0&
#2
b00000000000000000000000000000001 #
1&
#3
0&
#4
1&
#5
0&
#6
1&
#7
0&
#8
1&
#9
0&
#10
b00000000000000000000000000000000 #
b00000000000000000000000000000001 $
b00000000000000000000000000000001 %
1&
0'
b00000000000000000000000000000001 )
#11
0&
#12
b00000000000000000000000000000001 #
b00000000000000000000000000000000 $
1&
#13
0&
#14
b00000000000000000000000000000001 $
1&
#15
0&
#16
b00000000000000000000000000000010 %
1&
b00000000000000000000000000000010 )
#17
0&
#18
b00000000000000000000000000000010 #
1&
#19
0&
#20
b00000000000000000000000000000010 $
b00000000000000000000000000000011 %
1&
b00000000000000000000000000000011 )
#21
0&
#22
b00000000000000000000000000000011 #
b00000000000000000000000000000100 %
1&
b00000000000000000000000000000100 )
#23
0&
#24
b00000000000000000000000000000100 #
b00000000000000000000000000000011 $
b00000000000000000000000000000101 %
1&
b00000000000000000000000000000101 )
#25
0&
#26
b00000000000000000000000000000101 #
b00000000000000000000000000000100 $
b00000000000000000000000000000111 %
1&
b00000000000000000000000000000111 )
#27
0&
#28
b00000000000000000000000000000111 #
b00000000000000000000000000000101 $
b00000000000000000000000000001001 %
1&
b00000000000000000000000000001001 )
#29
0&
#30
b00000000000000000000000000001001 #
b00000000000000000000000000000111 $
b00000000000000000000000000001100 %
1&
b00000000000000000000000000001100 )
#31
0&
#32
b00000000000000000000000000001100 #
b00000000000000000000000000001001 $
b00000000000000000000000000010000 %
1&
b00000000000000000000000000010000 )
#33
0&
#34
b00000000000000000000000000010000 #
b00000000000000000000000000001100 $
b00000000000000000000000000010101 %
1&
b00000000000000000000000000010101 )
#35
0&
#36
b00000000000000000000000000010101 #
b00000000000000000000000000010000 $
b00000000000000000000000000011100 %
1&
b00000000000000000000000000011100 )
#37
0&
#38
b00000000000000000000000000011100 #
b00000000000000000000000000010101 $
b00000000000000000000000000100101 %
1&
b00000000000000000000000000100101 )
#39
0&
#40
b00000000000000000000000000100101 #
b00000000000000000000000000011100 $
b00000000000000000000000000110001 %
1&
b00000000000000000000000000110001 )
#41
0&
#42
b00000000000000000000000000110001 #
b00000000000000000000000000100101 $
b00000000000000000000000001000001 %
1&
b00000000000000000000000001000001 )
#43
0&
#44
b00000000000000000000000001000001 #
b00000000000000000000000000110001 $
b00000000000000000000000001010110 %
1&
b00000000000000000000000001010110 )
#45
0&
#46
b00000000000000000000000001010110 #
b00000000000000000000000001000001 $
b00000000000000000000000001110010 %
1&
b00000000000000000000000001110010 )
#47
0&
#48
b00000000000000000000000001110010 #
b00000000000000000000000001010110 $
b00000000000000000000000010010111 %
1&
b00000000000000000000000010010111 )
#49
0&
#50
b00000000000000000000000010010111 #
b00000000000000000000000001110010 $
b00000000000000000000000011001000 %
1&
b00000000000000000000000011001000 )
#51
0&
#52
b00000000000000000000000011001000 #
b00000000000000000000000010010111 $
b00000000000000000000000100001001 %
1&
b00000000000000000000000100001001 )
#53
0&
#54
b00000000000000000000000100001001 #
b00000000000000000000000011001000 $
b00000000000000000000000101011111 %
1&
b00000000000000000000000101011111 )
#55
0&
#56
b00000000000000000000000101011111 #
b00000000000000000000000100001001 $
b00000000000000000000000111010001 %
1&
b00000000000000000000000111010001 )
#57
0&
#58
b00000000000000000000000111010001 #
b00000000000000000000000101011111 $
b00000000000000000000001001101000 %
1&
b00000000000000000000001001101000 )
#59
0&
#60
b00000000000000000000001001101000 #
b00000000000000000000000111010001 $
b00000000000000000000001100110000 %
1&
b00000000000000000000001100110000 )
#61
0&
#62
b00000000000000000000001100110000 #
b00000000000000000000001001101000 $
b00000000000000000000010000111001 %
1&
b00000000000000000000010000111001 )
#63
0&
#64
b00000000000000000000010000111001 #
b00000000000000000000001100110000 $
b00000000000000000000010110011000 %
1&
b00000000000000000000010110011000 )
#65
0&
#66
b00000000000000000000010110011000 #
b00000000000000000000010000111001 $
b00000000000000000000011101101001 %
1&
b00000000000000000000011101101001 )
#67
0&
#68
b00000000000000000000011101101001 #
b00000000000000000000010110011000 $
b00000000000000000000100111010001 %
1&
b00000000000000000000100111010001 )
#69
0&
#70
b00000000000000000000100111010001 #
b00000000000000000000011101101001 $
b00000000000000000000110100000001 %
1&
b00000000000000000000110100000001 )
#71
0&
#72
b00000000000000000000110100000001 #
b00000000000000000000100111010001 $
b00000000000000000001000100111010 %
1&
b00000000000000000001000100111010 )
#73
0&
#74
b00000000000000000001000100111010 #
b00000000000000000000110100000001 $
b00000000000000000001011011010010 %
1&
b00000000000000000001011011010010 )
#75
0&
#76
b00000000000000000001011011010010 #
b00000000000000000001000100111010 $
b00000000000000000001111000111011 %
1&
b00000000000000000001111000111011 )
#77
0&
#78
b00000000000000000001111000111011 #
b00000000000000000001011011010010 $
b00000000000000000010100000001100 %
1&
b00000000000000000010100000001100 )
#79
0&
#80
b00000000000000000010100000001100 #
b00000000000000000001111000111011 $
b00000000000000000011010100001101 %
1&
b00000000000000000011010100001101 )
#81
0&
#82
b00000000000000000011010100001101 #
b00000000000000000010100000001100 $
b00000000000000000100011001000111 %
1&
b00000000000000000100011001000111 )
#83
0&
#84
b00000000000000000100011001000111 #
b00000000000000000011010100001101 $
b00000000000000000101110100011001 %
1&
b00000000000000000101110100011001 )
#85
0&
#86
b00000000000000000101110100011001 #
b00000000000000000100011001000111 $
b00000000000000000111101101010100 %
1&
b00000000000000000111101101010100 )
#87
0&
#88
b00000000000000000111101101010100 #
b00000000000000000101110100011001 $
b00000000000000001010001101100000 %
1&
b00000000000000001010001101100000 )
#89
0&
#90
b00000000000000001010001101100000 #
b00000000000000000111101101010100 $
b00000000000000001101100001101101 %
1&
b00000000000000001101100001101101 )
#91
0&
#92
b00000000000000001101100001101101 #
b00000000000000001010001101100000 $
b00000000000000010001111010110100 %
1&
b00000000000000010001111010110100 )
#93
0&
#94
b00000000000000010001111010110100 #
b00000000000000001101100001101101 $
b00000000000000010111101111001101 %
1&
b00000000000000010111101111001101 )
#95
0&
#96
b00000000000000010111101111001101 #
b00000000000000010001111010110100 $
b00000000000000011111011100100001 %
1&
b00000000000000011111011100100001 )
#97
0&
#98
b00000000000000011111011100100001 #
b00000000000000010111101111001101 $
b00000000000000101001101010000001 %
1&
b00000000000000101001101010000001 )
#99
0&
#100
b00000000000000101001101010000001 #
b00000000000000011111011100100001 $
b00000000000000110111001011101110 %
1&
b00000000000000110111001011101110 )
#101
0&
#102
b00000000000000110111001011101110 #
b00000000000000101001101010000001 $
b00000000000001001001000110100010 %
1&
b00000000000001001001000110100010 )
#103
0&
#104
b00000000000001001001000110100010 #
b00000000000000110111001011101110 $
b00000000000001100000110101101111 %
1&
b00000000000001100000110101101111 )
#105
0&
#106
b00000000000001100000110101101111 #
b00000000000001001001000110100010 $
b00000000000010000000010010010000 %
1&
b00000000000010000000010010010000 )
#107
0&
#108
b00000000000010000000010010010000 #
b00000000000001100000110101101111 $
b00000000000010101001111100010001 %
1&
b00000000000010101001111100010001 )
#109
0&
#110
b00000000000010101001111100010001 #
b00000000000010000000010010010000 $
b00000000000011100001000111111111 %
1&
b00000000000011100001000111111111 )
#111
0&
#112
b00000000000011100001000111111111 #
b00000000000010101001111100010001 $
b00000000000100101010001110100001 %
1&
b00000000000100101010001110100001 )
#113
0&
#114
b00000000000100101010001110100001 #
b00000000000011100001000111111111 $
b00000000000110001011000100010000 %
1&
b00000000000110001011000100010000 )
#115
0&
#116
b00000000000110001011000100010000 #
b00000000000100101010001110100001 $
b00000000001000001011010110100000 %
1&
b00000000001000001011010110100000 )
#117
0&
#118
b00000000001000001011010110100000 #
b00000000000110001011000100010000 $
b00000000001010110101010010110001 %
1&
b00000000001010110101010010110001 )
#119
0&
#120
b00000000001010110101010010110001 #
b00000000001000001011010110100000 $
b00000000001110010110011010110000 %
1&
b00000000001110010110011010110000 )
#121
0&
#122
b00000000001110010110011010110000 #
b00000000001010110101010010110001 $
b00000000010011000000101001010001 %
1&
b00000000010011000000101001010001 )
#123
0&
#124
b00000000010011000000101001010001 #
b00000000001110010110011010110000 $
b00000000011001001011101101100001 %
1&
b00000000011001001011101101100001 )
#125
0&
#126
b00000000011001001011101101100001 #
b00000000010011000000101001010001 $
b00000000100001010111000100000001 %
1&
b00000000100001010111000100000001 )
#127
0&
#128
b00000000100001010111000100000001 #
b00000000011001001011101101100001 $
b00000000101100001100010110110010 %
1&
b00000000101100001100010110110010 )
#129
0&
#130
b00000000101100001100010110110010 #
b00000000100001010111000100000001 $
b00000000111010100010110001100010 %
1&
b00000000111010100010110001100010 )
#131
0&
#132
b00000000111010100010110001100010 #
b00000000101100001100010110110010 $
b00000001001101100011011010110011 %
1&
b00000001001101100011011010110011 )
#133
0&
#134
b00000001001101100011011010110011 #
b00000000111010100010110001100010 $
b00000001100110101111001000010100 %
1&
b00000001100110101111001000010100 )
#135
0&
#136
b00000001100110101111001000010100 #
b00000001001101100011011010110011 $
b00000010001000000110001100010101 %
1&
b00000010001000000110001100010101 )
#137
0&
#138
b00000010001000000110001100010101 #
b00000001100110101111001000010100 $
b00000010110100010010100011000111 %
1&
b00000010110100010010100011000111 )
#139
0&
#140
b00000010110100010010100011000111 #
b00000010001000000110001100010101 $
b00000011101110110101010100101001 %
1&
b00000011101110110101010100101001 )
#141
0&
#142
b00000011101110110101010100101001 #
b00000010110100010010100011000111 $
b00000100111100011000101111011100 %
1&
b00000100111100011000101111011100 )
#143
0&
#144
b00000100111100011000101111011100 #
b00000011101110110101010100101001 $
b00000110100011000111110111110000 %
1&
b00000110100011000111110111110000 )
#145
0&
#146
b00000110100011000111110111110000 #
b00000100111100011000101111011100 $
b00001000101011001110000100000101 %
1&
b00001000101011001110000100000101 )
#147
0&
#148
b00001000101011001110000100000101 #
b00000110100011000111110111110000 $
b00001011011111100000100111001100 %
1&
b00001011011111100000100111001100 )
#149
0&
#150
b00001011011111100000100111001100 #
b00001000101011001110000100000101 $
b00001111001110010101111011110101 %
1&
b00001111001110010101111011110101 )
#151
0&
#152
b00001111001110010101111011110101 #
b00001011011111100000100111001100 $
b00010100001010101110101011010001 %
1&
b00010100001010101110101011010001 )
#153
0&
#154
b00010100001010101110101011010001 #
b00001111001110010101111011110101 $
b00011010101101110110100011000001 %
1&
b00011010101101110110100011000001 )
#155
0&
#156
b00011010101101110110100011000001 #
b00010100001010101110101011010001 $
b00100011011001000100100111000110 %
1&
b00100011011001000100100111000110 )
#157
0&
#158
b00100011011001000100100111000110 #
b00011010101101110110100011000001 $
b00101110111000100101001110010010 %
1&
b00101110111000100101001110010010 )
#159
0&
#160
b00101110111000100101001110010010 #
b00100011011001000100100111000110 $
b00111110000110111011001010000111 %
1&
b00111110000110111011001010000111 )
#161
0&
#162
b00111110000110111011001010000111 #
b00101110111000100101001110010010 $
b01010010010001101001110101011000 %
1&
b01010010010001101001110101011000 )
#163
0&
#164
b01010010010001101001110101011000 #
b00111110000110111011001010000111 $
b01101100111111100000011000011001 %
1&
b01101100111111100000011000011001 )
#165
0&
#166
b01101100111111100000011000011001 #
b01010010010001101001110101011000 $
b10010000011000100100111111011111 %
1&
b10010000011000100100111111011111 )
#167
0&
#168
b10010000011000100100111111011111 #
b01101100111111100000011000011001 $
b10111111010001001010001101110001 %
1&
b10111111010001001010001101110001 )
#169
0&
#170
b10111111010001001010001101110001 #
b10010000011000100100111111011111 $
b11111101011000000101010111111000 %
1&
b11111101011000000101010111111000 )
#171
0&
#172
b11111101011000000101010111111000 #
b10111111010001001010001101110001 $
b01001111101001101111001101010000 %
1&
b01001111101001101111001101010000 )
#173
0&
#174
b01001111101001101111001101010000 #
b11111101011000000101010111111000 $
b10111100101001001111100101101001 %
1&
b10111100101001001111100101101001 )
#175
0&
#176
b10111100101001001111100101101001 #
b01001111101001101111001101010000 $
b01001101000001110100100101001000 %
1&
b01001101000001110100100101001000 )
#177
0&
#178
b01001101000001110100100101001000 #
b10111100101001001111100101101001 $
b00001100010010111110110010111001 %
1&
b00001100010010111110110010111001 )
#179
0&
#180
b00001100010010111110110010111001 #
b01001101000001110100100101001000 $
b00001001101011000100001010110001 %
1&
b00001001101011000100001010110001 )
#181
0&
#182
b00001001101011000100001010110001 #
b00001100010010111110110010111001 $
b01011001010100110011011000000001 %
1&
b01011001010100110011011000000001 )
#183
0&
#184
b01011001010100110011011000000001 #
b00001001101011000100001010110001 $
b00010101111110000010111101101010 %
1&
b00010101111110000010111101101010 )
#185
0&
#186
b00010101111110000010111101101010 #
b01011001010100110011011000000001 $
b01100010111111110111100010110010 %
1&
b01100010111111110111100010110010 )
#187
0&
#188
b01100010111111110111100010110010 #
b00010101111110000010111101101010 $
b01101111010010110110010101101011 %
1&
b01101111010010110110010101101011 )
#189
0&
#190
b01101111010010110110010101101011 #
b01100010111111110111100010110010 $
b01111000111101111010100000011100 %
1&
b01111000111101111010100000011100 )
#191
0&
#192
b01111000111101111010100000011100 #
b01101111010010110110010101101011 $
b11010010010010101101111000011101 %
1&
b11010010010010101101111000011101 )
#193
0&
#194
b11010010010010101101111000011101 #
b01111000111101111010100000011100 $
b11101000010000110000110110000111 %
1&
b11101000010000110000110110000111 )
#195
0&
#196
b11101000010000110000110110000111 #
b11010010010010101101111000011101 $
b01001011010000101000011000111001 %
1&
b01001011010000101000011000111001 )
#197
0&
#198
b01001011010000101000011000111001 #
b11101000010000110000110110000111 $
b10111010100011011110101110100100 %
1&
b10111010100011011110101110100100 )
#199
0&
#200
b10111010100011011110101110100100 #
b01001011010000101000011000111001 $
b00110011100001011001001111000000 %
1&
b00110011100001011001001111000000 )
#201
0&
#202
b00110011100001011001001111000000 #
b10111010100011011110101110100100 $
b00000101110100000111000111011101 %
1&
b00000101110100000111000111011101 )
#203
0&
#204
b00000101110100000111000111011101 #
b00110011100001011001001111000000 $
b11101110000100110111111101100100 %
1&
b11101110000100110111111101100100 )
#205
0&
#206
b11101110000100110111111101100100 #
b00000101110100000111000111011101 $
b00111001010101100000010110011101 %
1&
b00111001010101100000010110011101 )
#207
0&
#208
b00111001010101100000010110011101 #
b11101110000100110111111101100100 $
b11110011111000111111000101000001 %
1&
b11110011111000111111000101000001 )
#209
0&
#210
b11110011111000111111000101000001 #
b00111001010101100000010110011101 $
b00100111011010011000010100000001 %
1&
b00100111011010011000010100000001 )
#211
0&
#212
b00100111011010011000010100000001 #
b11110011111000111111000101000001 $
b00101101001110011111011011011110 %
1&
b00101101001110011111011011011110 )
#213
0&
#214
b00101101001110011111011011011110 #
b00100111011010011000010100000001 $
b00011011010011010111011001000010 %
1&
b00011011010011010111011001000010 )
#215
0&
#216
b00011011010011010111011001000010 #
b00101101001110011111011011011110 $
b01010100101000110111101111011111 %
1&
b01010100101000110111101111011111 )
#217
0&
#218
b01010100101000110111101111011111 #
b00011011010011010111011001000010 $
b01001000100001110110110100100000 %
1&
b01001000100001110110110100100000 )
#219
0&
#220
b01001000100001110110110100100000 #
b01010100101000110111101111011111 $
b01101111111100001111001000100001 %
1&
b01101111111100001111001000100001 )
#221
0&
#222
b01101111111100001111001000100001 #
b01001000100001110110110100100000 $
b10011101001010101110100011111111 %
1&
b10011101001010101110100011111111 )
#223
0&
#224
b10011101001010101110100011111111 #
b01101111111100001111001000100001 $
b10111000011110000101111101000001 %
1&
b10111000011110000101111101000001 )
#225
0&
#226
b10111000011110000101111101000001 #
b10011101001010101110100011111111 $
b00001101000110111101101100100000 %
1&
b00001101000110111101101100100000 )
#227
0&
#228
b00001101000110111101101100100000 #
b10111000011110000101111101000001 $
b01010101101000110100100001000000 %
1&
b01010101101000110100100001000000 )
#229
0&
#230
b01010101101000110100100001000000 #
b00001101000110111101101100100000 $
b11000101100101000011101001100001 %
1&
b11000101100101000011101001100001 )
#231
0&
#232
b11000101100101000011101001100001 #
b01010101101000110100100001000000 $
b01100010101111110010001101100000 %
1&
b01100010101111110010001101100000 )
#233
0&
#234
b01100010101111110010001101100000 #
b11000101100101000011101001100001 $
b00011011001101111000001010100001 %
1&
b00011011001101111000001010100001 )
#235
0&
#236
b00011011001101111000001010100001 #
b01100010101111110010001101100000 $
b00101000010100110101110111000001 %
1&
b00101000010100110101110111000001 )
#237
0&
#238
b00101000010100110101110111000001 #
b00011011001101111000001010100001 $
b01111101111101101010011000000001 %
1&
b01111101111101101010011000000001 )
#239
0&
#240
b01111101111101101010011000000001 #
b00101000010100110101110111000001 $
b01000011100010101110000001100010 %
1&
b01000011100010101110000001100010 )
#241
0&
#242
b01000011100010101110000001100010 #
b01111101111101101010011000000001 $
b10100110010010100000001111000010 %
1&
b10100110010010100000001111000010 )
#243
0&
#244
b10100110010010100000001111000010 #
b01000011100010101110000001100010 $
b11000001100000011000011001100011 %
1&
b11000001100000011000011001100011 )
#245
0&
#246
b11000001100000011000011001100011 #
b10100110010010100000001111000010 $
b11101001110101001110010000100100 %
1&
b11101001110101001110010000100100 )
#247
0&
#248
b11101001110101001110010000100100 #
b11000001100000011000011001100011 $
b01100111110010111000101000100101 %
1&
b01100111110010111000101000100101 )
#249
0&
#250
b01100111110010111000101000100101 #
b11101001110101001110010000100100 $
b10101011010101100110101010000111 %
1&
b10101011010101100110101010000111 )
#251
0&
#252
b10101011010101100110101010000111 #
b01100111110010111000101000100101 $
b01010001101000000110111001001001 %
1&
b01010001101000000110111001001001 )
#253
0&
#254
b01010001101000000110111001001001 #
b10101011010101100110101010000111 $
b00010011001000011111010010101100 %
1&
b00010011001000011111010010101100 )
#255
0&
#256
b00010011001000011111010010101100 #
b01010001101000000110111001001001 $
b11111100111101101101100011010000 %
1&
b11111100111101101101100011010000 )
#257
0&
#258
b11111100111101101101100011010000 #
b00010011001000011111010010101100 $
b01100100110000100110001011110101 %
1&
b01100100110000100110001011110101 )
#259
0&
#260
b01100100110000100110001011110101 #
b11111100111101101101100011010000 $
b00010000000110001100110101111100 %
1&
b00010000000110001100110101111100 )
#261
0&
#262
b00010000000110001100110101111100 #
b01100100110000100110001011110101 $
b01100001101110010011101111000101 %
1&
b01100001101110010011101111000101 )
#263
0&
#264
b01100001101110010011101111000101 #
b00010000000110001100110101111100 $
b01110100110110110011000001110001 %
1&
b01110100110110110011000001110001 )
#265
0&
#266
b01110100110110110011000001110001 #
b01100001101110010011101111000101 $
b01110001110100100000100101000001 %
1&
b01110001110100100000100101000001 )
#267
0&
#268
b01110001110100100000100101000001 #
b01110100110110110011000001110001 $
b11010110100101000110110000110110 %
1&
b11010110100101000110110000110110 )
#269
0&
#270
b11010110100101000110110000110110 #
b01110001110100100000100101000001 $
b11100110101011010011100110110010 %
1&
b11100110101011010011100110110010 )
#271
0&
#272
b11100110101011010011100110110010 #
b11010110100101000110110000110110 $
b01001000011001100111010101110111 %
1&
b01001000011001100111010101110111 )
#273
0&
#274
b01001000011001100111010101110111 #
b11100110101011010011100110110010 $
b10111101010000011010010111101000 %
1&
b10111101010000011010010111101000 )
#275
0&
#276
b10111101010000011010010111101000 #
b01001000011001100111010101110111 $
b00101111000100111010111100101001 %
1&
b00101111000100111010111100101001 )
#277
0&
#278
b00101111000100111010111100101001 #
b10111101010000011010010111101000 $
b00000101101010000001101101011111 %
1&
b00000101101010000001101101011111 )
#279
0&
#280
b00000101101010000001101101011111 #
b00101111000100111010111100101001 $
b11101100010101010101010100010001 %
1&
b11101100010101010101010100010001 )
#281
0&
#282
b11101100010101010101010100010001 #
b00000101101010000001101101011111 $
b00110100101110111100101010001000 %
1&
b00110100101110111100101010001000 )
#283
0&
#284
b00110100101110111100101010001000 #
b11101100010101010101010100010001 $
b11110001111111010111000001110000 %
1&
b11110001111111010111000001110000 )
#285
0&
#286
b11110001111111010111000001110000 #
b00110100101110111100101010001000 $
b00100001000100010001111110011001 %
1&
b00100001000100010001111110011001 )
#287
0&
#288
b00100001000100010001111110011001 #
b11110001111111010111000001110000 $
b00100110101110010011101011111000 %
1&
b00100110101110010011101011111000 )
#289
0&
#290
b00100110101110010011101011111000 #
b00100001000100010001111110011001 $
b00010011000011101001000000001001 %
1&
b00010011000011101001000000001001 )
#291
0&
#292
b00010011000011101001000000001001 #
b00100110101110010011101011111000 $
b01000111110010100101101010010001 %
1&
b01000111110010100101101010010001 )
#293
0&
#294
b01000111110010100101101010010001 #
b00010011000011101001000000001001 $
b00111001110001111100101100000001 %
1&
b00111001110001111100101100000001 )
#295
0&
#296
b00111001110001111100101100000001 #
b01000111110010100101101010010001 $
b01011010110110001110101010011010 %
1&
b01011010110110001110101010011010 )
#297
0&
#298
b01011010110110001110101010011010 #
b00111001110001111100101100000001 $
b10000001100100100010010110010010 %
1&
b10000001100100100010010110010010 )
#299
0&
#300
b10000001100100100010010110010010 #
b01011010110110001110101010011010 $
b10010100101000001011010110011011 %
1&
b10010100101000001011010110011011 )
#301
0&
#302
b10010100101000001011010110011011 #
b10000001100100100010010110010010 $
b11011100011010110001000000101100 %
1&
b11011100011010110001000000101100 )
#303
0&
#304
b11011100011010110001000000101100 #
b10010100101000001011010110011011 $
b00010110001100101101101100101101 %
1&
b00010110001100101101101100101101 )
#305
0&
#306
b00010110001100101101101100101101 #
b11011100011010110001000000101100 $
b01110001000010111100010111000111 %
1&
b01110001000010111100010111000111 )
#307
0&
#308
b01110001000010111100010111000111 #
b00010110001100101101101100101101 $
b11110010100111011110101101011001 %
1&
b11110010100111011110101101011001 )
#309
0&
#310
b11110010100111011110101101011001 #
b01110001000010111100010111000111 $
b10000111001111101010000011110100 %
1&
b10000111001111101010000011110100 )
#311
0&
#312
b10000111001111101010000011110100 #
b11110010100111011110101101011001 $
b01100011101010011011000100100000 %
1&
b01100011101010011011000100100000 )
#313
0&
#314
b01100011101010011011000100100000 #
b10000111001111101010000011110100 $
b01111001110111001000110001001101 %
1&
b01111001110111001000110001001101 )
#315
0&
#316
b01111001110111001000110001001101 #
b01100011101010011011000100100000 $
b11101010111010000101001000010100 %
1&
b11101010111010000101001000010100 )
#317
0&
#318
b11101010111010000101001000010100 #
b01111001110111001000110001001101 $
b11011101100001100011110101101101 %
1&
b11011101100001100011110101101101 )
#319
0&
#320
b11011101100001100011110101101101 #
b11101010111010000101001000010100 $
b01100100110001001101111001100001 %
1&
b01100100110001001101111001100001 )
#321
0&
#322
b01100100110001001101111001100001 #
b11011101100001100011110101101101 $
b11001000011011101000111110000001 %
1&
b11001000011011101000111110000001 )
#323
0&
#324
b11001000011011101000111110000001 #
b01100100110001001101111001100001 $
b01000010010010110001101111001110 %
1&
b01000010010010110001101111001110 )
#325
0&
#326
b01000010010010110001101111001110 #
b11001000011011101000111110000001 $
b00101101001100110110110111100010 %
1&
b00101101001100110110110111100010 )
#327
0&
#328
b00101101001100110110110111100010 #
b01000010010010110001101111001110 $
b00001010101110011010101101001111 %
1&
b00001010101110011010101101001111 )
#329
0&
#330
b00001010101110011010101101001111 #
b00101101001100110110110111100010 $
b01101111011111101000100110110000 %
1&
b01101111011111101000100110110000 )
#331
0&
#332
b01101111011111101000100110110000 #
b00001010101110011010101101001111 $
b00110111111011010001100100110001 %
1&
b00110111111011010001100100110001 )
#333
0&
#334
b00110111111011010001100100110001 #
b01101111011111101000100110110000 $
b01111010001110000011010011111111 %
1&
b01111010001110000011010011111111 )
#335
0&
#336
b01111010001110000011010011111111 #
b00110111111011010001100100110001 $
b10100111011010111010001011100001 %
1&
b10100111011010111010001011100001 )
#337
0&
#338
b10100111011010111010001011100001 #
b01111010001110000011010011111111 $
b10110010001001010100111000110000 %
1&
b10110010001001010100111000110000 )
#339
0&
#340
b10110010001001010100111000110000 #
b10100111011010111010001011100001 $
b00100001101000111101011111100000 %
1&
b00100001101000111101011111100000 )
#341
0&
#342
b00100001101000111101011111100000 #
b10110010001001010100111000110000 $
b01011001100100001111000100010001 %
1&
b01011001100100001111000100010001 )
#343
0&
#344
b01011001100100001111000100010001 #
b00100001101000111101011111100000 $
b11010011110010010010011000010000 %
1&
b11010011110010010010011000010000 )
#345
0&
#346
b11010011110010010010011000010000 #
b01011001100100001111000100010001 $
b01111011001101001100100011110001 %
1&
b01111011001101001100100011110001 )
#347
0&
#348
b01111011001101001100100011110001 #
b11010011110010010010011000010000 $
b00101101010110100001011100100001 %
1&
b00101101010110100001011100100001 )
#349
0&
#350
b00101101010110100001011100100001 #
b01111011001101001100100011110001 $
b01001110111111011110111100000001 %
1&
b01001110111111011110111100000001 )
#351
0&
#352
b01001110111111011110111100000001 #
b00101101010110100001011100100001 $
b10101000100011101110000000010010 %
1&
b10101000100011101110000000010010 )
#353
0&
#354
b10101000100011101110000000010010 #
b01001110111111011110111100000001 $
b01111100010110000000011000100010 %
1&
b01111100010110000000011000100010 )
#355
0&
#356
b01111100010110000000011000100010 #
b10101000100011101110000000010010 $
b11110111100011001100111100010011 %
1&
b11110111100011001100111100010011 )
#357
0&
#358
b11110111100011001100111100010011 #
b01111100010110000000011000100010 $
b00100100111001101110011000110100 %
1&
b00100100111001101110011000110100 )
#359
0&
#360
b00100100111001101110011000110100 #
b11110111100011001100111100010011 $
b01110011111001001101010100110101 %
1&
b01110011111001001101010100110101 )
#361
0&
#362
b01110011111001001101010100110101 #
b00100100111001101110011000110100 $
b00011100011100111011010101000111 %
1&
b00011100011100111011010101000111 )
#363
0&
#364
b00011100011100111011010101000111 #
b01110011111001001101010100110101 $
b10011000110010111011101101101001 %
1&
b10011000110010111011101101101001 )
#365
0&
#366
b10011000110010111011101101101001 #
b00011100011100111011010101000111 $
b10010000010110001000101001111100 %
1&
b10010000010110001000101001111100 )
#367
0&
#368
b10010000010110001000101001111100 #
b10011000110010111011101101101001 $
b10110101001111110111000010110000 %
1&
b10110101001111110111000010110000 )
#369
0&
#370
b10110101001111110111000010110000 #
b10010000010110001000101001111100 $
b00101001001001000100010111100101 %
1&
b00101001001001000100010111100101 )
#371
0&
#372
b00101001001001000100010111100101 #
b10110101001111110111000010110000 $
b01000101100101111111101100101100 %
1&
b01000101100101111111101100101100 )
#373
0&
#374
b01000101100101111111101100101100 #
b00101001001001000100010111100101 $
b11011110011000111011011010010101 %
1&
b11011110011000111011011010010101 )
#375
0&
#376
b11011110011000111011011010010101 #
b01000101100101111111101100101100 $
b01101110101111000100000100010001 %
1&
b01101110101111000100000100010001 )
#377
0&
#378
b01101110101111000100000100010001 #
b11011110011000111011011010010101 $
b00100011111110111011000111000001 %
1&
b00100011111110111011000111000001 )
#379
0&
#380
b00100011111110111011000111000001 #
b01101110101111000100000100010001 $
b01001101000111111111011110100110 %
1&
b01001101000111111111011110100110 )
#381
0&
#382
b01001101000111111111011110100110 #
b00100011111110111011000111000001 $
b10010010101101111111001011010010 %
1&
b10010010101101111111001011010010 )
#383
0&
#384
b10010010101101111111001011010010 #
b01001101000111111111011110100110 $
b01110001000110111010100101100111 %
1&
b01110001000110111010100101100111 )
#385
0&
#386
b01110001000110111010100101100111 #
b10010010101101111111001011010010 $
b11011111110101111110101001111000 %
1&
b11011111110101111110101001111000 )
#387
0&
#388
b11011111110101111110101001111000 #
b01110001000110111010100101100111 $
b00000011110100111001110000111001 %
1&
b00000011110100111001110000111001 )
#389
0&
#390
b00000011110100111001110000111001 #
b11011111110101111110101001111000 $
b01010000111100111001001111011111 %
1&
b01010000111100111001001111011111 )
#391
0&
#392
b01010000111100111001001111011111 #
b00000011110100111001110000111001 $
b11100011101010111000011010110001 %
1&
b11100011101010111000011010110001 )
#393
0&
#394
b11100011101010111000011010110001 #
b01010000111100111001001111011111 $
b01010100110001110011000000011000 %
1&
b01010100110001110011000000011000 )
#395
0&
#396
b01010100110001110011000000011000 #
b11100011101010111000011010110001 $
b00110100100111110001101010010000 %
1&
b00110100100111110001101010010000 )
#397
0&
#398
b00110100100111110001101010010000 #
b01010100110001110011000000011000 $
b00111000011100101011011011001001 %
1&
b00111000011100101011011011001001 )
#399
0&
#400
b00111000011100101011011011001001 #
b00110100100111110001101010010000 $
b10001001011001100100101010101000 %
1&
b10001001011001100100101010101000 )
#401
0&
#402
b10001001011001100100101010101000 #
b00111000011100101011011011001001 $
b01101101000100011101000101011001 %
1&
b01101101000100011101000101011001 )
#403
0&
#404
b01101101000100011101000101011001 #
b10001001011001100100101010101000 $
b11000001110110010000000101110001 %
1&
b11000001110110010000000101110001 )
#405
0&
